<dashboard version="1.1" theme="dark">
  <label>Asset Discovery</label>
  <description>Discover Splunk indexes and sourcetypes that contain data matching your monitored endpoints</description>
  
  <!-- Load configuration from KV Store -->
  <search id="load_config">
    <query>| inputlookup ping_monitor_settings_lookup 
| search _key="global" 
| head 1
| eval index=coalesce(index, "ping"), sourcetype=coalesce(sourcetype, "ping_monitor"), metrics_index=coalesce(metrics_index, "ping_metrics")</query>
    <earliest>-1m</earliest>
    <latest>now</latest>
    <done>
      <set token="pm_index">$result.index$</set>
      <set token="pm_sourcetype">$result.sourcetype$</set>
      <set token="pm_metrics_index">$result.metrics_index$</set>
    </done>
  </search>
  
  <init>
    <set token="pm_index">ping</set>
    <set token="pm_sourcetype">ping_monitor</set>
    <set token="pm_metrics_index">ping_metrics</set>
    <set token="show_events">true</set>
    <set token="search_asset"></set>
  </init>
  
  <fieldset submitButton="false" autoRun="true">
    <input type="dropdown" token="data_source" searchWhenChanged="true">
      <label>Data Source</label>
      <choice value="events">Events</choice>
      <choice value="metrics">Metrics</choice>
      <choice value="combined">Combined</choice>
      <default>events</default>
      <change>
        <condition value="events">
          <set token="show_events">true</set>
          <unset token="show_metrics"></unset>
          <unset token="show_combined"></unset>
        </condition>
        <condition value="metrics">
          <unset token="show_events"></unset>
          <set token="show_metrics">true</set>
          <unset token="show_combined"></unset>
        </condition>
        <condition value="combined">
          <set token="show_events">true</set>
          <set token="show_metrics">true</set>
          <set token="show_combined">true</set>
        </condition>
      </change>
    </input>
    <input type="time" token="time_range" searchWhenChanged="true">
      <label>Discovery Time Range</label>
      <default>
        <earliest>-24h@h</earliest>
        <latest>now</latest>
      </default>
    </input>
  </fieldset>

  <!-- Data Source Indicator -->
  <row>
    <panel>
      <html>
        <div style="padding: 10px; background: #1a1a2e; border-radius: 5px; text-align: center;">
          <span style="color: #6db7c6; font-weight: bold;">📊 Data Source:</span>
          <span style="color: #fff; margin-left: 10px;">$data_source|s$</span>
          <span style="color: #888; margin-left: 20px;">
            Events Index: <strong>$pm_index$</strong> | 
            Metrics Index: <strong>$pm_metrics_index$</strong>
          </span>
        </div>
      </html>
    </panel>
  </row>

  <!-- Row 1: Summary Statistics - EVENTS -->
  <row depends="$show_events$">
    <panel>
      <single>
        <title>Total Monitored Assets (Events)</title>
        <search>
          <query>index=$pm_index$ sourcetype=$pm_sourcetype$ record_type=summary
| stats dc(hostname) as asset_count</query>
          <earliest>$time_range.earliest$</earliest>
          <latest>$time_range.latest$</latest>
        </search>
        <option name="colorMode">block</option>
        <option name="drilldown">none</option>
        <option name="rangeColors">["0x53a051","0x53a051"]</option>
        <option name="rangeValues">[0]</option>
        <option name="useColors">1</option>
      </single>
    </panel>
    <panel>
      <single>
        <title>Unique IP Addresses (Events)</title>
        <search>
          <query>index=$pm_index$ sourcetype=$pm_sourcetype$ record_type=summary
| stats dc(target_ip) as ip_count</query>
          <earliest>$time_range.earliest$</earliest>
          <latest>$time_range.latest$</latest>
        </search>
        <option name="colorMode">block</option>
        <option name="drilldown">none</option>
        <option name="rangeColors">["0x65a637","0x65a637"]</option>
        <option name="rangeValues">[0]</option>
        <option name="useColors">1</option>
      </single>
    </panel>
    <panel>
      <single>
        <title>Unique Groups (Events)</title>
        <search>
          <query>index=$pm_index$ sourcetype=$pm_sourcetype$ record_type=summary
| stats dc(group) as group_count</query>
          <earliest>$time_range.earliest$</earliest>
          <latest>$time_range.latest$</latest>
        </search>
        <option name="colorMode">block</option>
        <option name="drilldown">none</option>
        <option name="rangeColors">["0x6db7c6","0x6db7c6"]</option>
        <option name="rangeValues">[0]</option>
        <option name="useColors">1</option>
      </single>
    </panel>
    <panel>
      <single>
        <title>Entity Types (Events)</title>
        <search>
          <query>index=$pm_index$ sourcetype=$pm_sourcetype$ record_type=summary
| stats dc(entitytype) as type_count</query>
          <earliest>$time_range.earliest$</earliest>
          <latest>$time_range.latest$</latest>
        </search>
        <option name="colorMode">block</option>
        <option name="drilldown">none</option>
        <option name="rangeColors">["0xf8be34","0xf8be34"]</option>
        <option name="rangeValues">[0]</option>
        <option name="useColors">1</option>
      </single>
    </panel>
  </row>

  <!-- Row 1: Summary Statistics - METRICS -->
  <row depends="$show_metrics$" rejects="$show_combined$">
    <panel>
      <single>
        <title>Total Monitored Assets (Metrics)</title>
        <search>
          <query>| mstats count("ping.pings_sent") as count WHERE index="$pm_metrics_index$" BY hostname
| stats dc(hostname) as asset_count</query>
          <earliest>$time_range.earliest$</earliest>
          <latest>$time_range.latest$</latest>
        </search>
        <option name="colorMode">block</option>
        <option name="drilldown">none</option>
        <option name="rangeColors">["0x6db7c6","0x6db7c6"]</option>
        <option name="rangeValues">[0]</option>
        <option name="useColors">1</option>
      </single>
    </panel>
    <panel>
      <single>
        <title>Unique IP Addresses (Metrics)</title>
        <search>
          <query>| mstats count("ping.pings_sent") as count WHERE index="$pm_metrics_index$" BY target_ip
| stats dc(target_ip) as ip_count</query>
          <earliest>$time_range.earliest$</earliest>
          <latest>$time_range.latest$</latest>
        </search>
        <option name="colorMode">block</option>
        <option name="drilldown">none</option>
        <option name="rangeColors">["0x6db7c6","0x6db7c6"]</option>
        <option name="rangeValues">[0]</option>
        <option name="useColors">1</option>
      </single>
    </panel>
    <panel>
      <single>
        <title>Unique Groups (Metrics)</title>
        <search>
          <query>| mstats count("ping.pings_sent") as count WHERE index="$pm_metrics_index$" BY group
| stats dc(group) as group_count</query>
          <earliest>$time_range.earliest$</earliest>
          <latest>$time_range.latest$</latest>
        </search>
        <option name="colorMode">block</option>
        <option name="drilldown">none</option>
        <option name="rangeColors">["0x6db7c6","0x6db7c6"]</option>
        <option name="rangeValues">[0]</option>
        <option name="useColors">1</option>
      </single>
    </panel>
    <panel>
      <single>
        <title>Metric Data Points</title>
        <search>
          <query>| mstats count("ping.pings_sent") as count WHERE index="$pm_metrics_index$"</query>
          <earliest>$time_range.earliest$</earliest>
          <latest>$time_range.latest$</latest>
        </search>
        <option name="colorMode">block</option>
        <option name="drilldown">none</option>
        <option name="rangeColors">["0x6db7c6","0x6db7c6"]</option>
        <option name="rangeValues">[0]</option>
        <option name="useColors">1</option>
      </single>
    </panel>
  </row>

  <!-- Row 2: Asset Inventory - EVENTS -->
  <row depends="$show_events$">
    <panel>
      <title>Monitored Assets from Ping Data (Events)</title>
      <table>
        <search>
          <query>index=$pm_index$ sourcetype=$pm_sourcetype$ record_type=summary
| stats latest(target_ip) as ip_address,
        latest(group) as group,
        latest(entitytype) as entity_type,
        latest(device) as device,
        latest(vendor) as vendor,
        latest(description) as description
        by hostname
| table hostname, ip_address, group, entity_type, device, vendor, description
| sort hostname</query>
          <earliest>$time_range.earliest$</earliest>
          <latest>$time_range.latest$</latest>
        </search>
        <option name="drilldown">none</option>
        <option name="count">20</option>
      </table>
    </panel>
  </row>

  <!-- Row 2: Asset Inventory - METRICS -->
  <row depends="$show_metrics$" rejects="$show_combined$">
    <panel>
      <title>Monitored Assets from Ping Data (Metrics)</title>
      <table>
        <search>
          <query>| mstats count("ping.pings_sent") as pings WHERE index="$pm_metrics_index$" BY hostname, target_ip, group
| stats first(target_ip) as ip_address, first(group) as group, sum(pings) as total_pings by hostname
| table hostname, ip_address, group, total_pings
| sort hostname</query>
          <earliest>$time_range.earliest$</earliest>
          <latest>$time_range.latest$</latest>
        </search>
        <option name="drilldown">none</option>
        <option name="count">20</option>
      </table>
    </panel>
  </row>

  <!-- Row 3: Discover Indexes with Matching IPs -->
  <row depends="$show_events$">
    <panel>
      <title>Indexes Containing Your Monitored IP Addresses</title>
      <html>
        <p style="color:#999;margin-bottom:10px;">Shows indexes where your monitored IP addresses appear in src_ip, dest_ip, src, dest, or ip fields</p>
      </html>
      <table>
        <search>
          <query>index=$pm_index$ sourcetype=$pm_sourcetype$ record_type=summary
| stats values(target_ip) as monitored_ips
| mvexpand monitored_ips
| head 20
| rename monitored_ips as search_ip
| map maxsearches=20 search="search index=* (src_ip=\"$search_ip$\" OR dest_ip=\"$search_ip$\" OR src=\"$search_ip$\" OR dest=\"$search_ip$\" OR ip=\"$search_ip$\") | stats count by index, sourcetype | eval matched_ip=\"$search_ip$\""
| stats sum(count) as matched_events, values(matched_ip) as matched_ips by index, sourcetype
| where matched_events > 0
| sort -matched_events
| head 20
| rename matched_events as "Events", matched_ips as "Matched IPs"</query>
          <earliest>$time_range.earliest$</earliest>
          <latest>$time_range.latest$</latest>
        </search>
        <option name="drilldown">none</option>
        <option name="count">20</option>
      </table>
    </panel>
  </row>

  <!-- Row 4: Discover Indexes with Matching Hostnames -->
  <row depends="$show_events$">
    <panel>
      <title>Indexes Containing Your Monitored Hostnames</title>
      <html>
        <p style="color:#999;margin-bottom:10px;">Shows indexes where your monitored hostnames appear in the host field or event data</p>
      </html>
      <table>
        <search>
          <query>index=$pm_index$ sourcetype=$pm_sourcetype$ record_type=summary
| stats values(hostname) as monitored_hosts
| mvexpand monitored_hosts
| head 20
| rename monitored_hosts as search_host
| map maxsearches=20 search="search index=* host=\"$search_host$\" | stats count by index, sourcetype | eval matched_host=\"$search_host$\""
| stats sum(count) as matched_events, values(matched_host) as matched_hosts by index, sourcetype
| where matched_events > 0
| sort -matched_events
| head 20
| rename matched_events as "Events", matched_hosts as "Matched Hosts"</query>
          <earliest>$time_range.earliest$</earliest>
          <latest>$time_range.latest$</latest>
        </search>
        <option name="drilldown">none</option>
        <option name="count">20</option>
      </table>
    </panel>
  </row>

  <!-- Row 5: Quick Discovery Search -->
  <row>
    <panel>
      <title>Quick Asset Search</title>
      <html>
        <p style="color:#999;margin-bottom:10px;">Enter an IP address or hostname to find all indexes/sourcetypes containing that asset, then press Enter</p>
      </html>
      <input type="text" token="search_asset" searchWhenChanged="true">
        <label>IP or Hostname</label>
        <default></default>
      </input>
    </panel>
  </row>
  
  <row depends="$search_asset$">
    <panel>
      <title>Search Results for: $search_asset$</title>
      <table>
        <search>
          <query>search index=* ("$search_asset$" OR host="*$search_asset$*" OR src_ip="$search_asset$" OR dest_ip="$search_asset$")
| stats count by index, sourcetype
| sort -count
| head 20
| rename count as "Matching Events"</query>
          <earliest>$time_range.earliest$</earliest>
          <latest>$time_range.latest$</latest>
        </search>
        <option name="drilldown">none</option>
        <option name="count">20</option>
      </table>
    </panel>
  </row>

  <!-- Row 6: Assets by Group - EVENTS -->
  <row depends="$show_events$">
    <panel>
      <title>Assets by Group (Events)</title>
      <chart>
        <search>
          <query>index=$pm_index$ sourcetype=$pm_sourcetype$ record_type=summary
| stats dc(hostname) as host_count by group
| sort -host_count</query>
          <earliest>$time_range.earliest$</earliest>
          <latest>$time_range.latest$</latest>
        </search>
        <option name="charting.chart">pie</option>
        <option name="charting.drilldown">none</option>
      </chart>
    </panel>
    <panel>
      <title>Assets by Entity Type (Events)</title>
      <chart>
        <search>
          <query>index=$pm_index$ sourcetype=$pm_sourcetype$ record_type=summary
| stats dc(hostname) as host_count by entitytype
| sort -host_count</query>
          <earliest>$time_range.earliest$</earliest>
          <latest>$time_range.latest$</latest>
        </search>
        <option name="charting.chart">pie</option>
        <option name="charting.drilldown">none</option>
      </chart>
    </panel>
  </row>

  <!-- Row 6: Assets by Group - METRICS -->
  <row depends="$show_metrics$" rejects="$show_combined$">
    <panel>
      <title>Assets by Group (Metrics)</title>
      <chart>
        <search>
          <query>| mstats count("ping.pings_sent") as count WHERE index="$pm_metrics_index$" BY hostname, group
| stats dc(hostname) as host_count by group
| sort -host_count</query>
          <earliest>$time_range.earliest$</earliest>
          <latest>$time_range.latest$</latest>
        </search>
        <option name="charting.chart">pie</option>
        <option name="charting.drilldown">none</option>
      </chart>
    </panel>
    <panel>
      <title>Data Points by Group (Metrics)</title>
      <chart>
        <search>
          <query>| mstats count("ping.pings_sent") as data_points WHERE index="$pm_metrics_index$" BY group
| sort -data_points</query>
          <earliest>$time_range.earliest$</earliest>
          <latest>$time_range.latest$</latest>
        </search>
        <option name="charting.chart">pie</option>
        <option name="charting.drilldown">none</option>
      </chart>
    </panel>
  </row>

</dashboard>
